{
  "Scenarios": [
    {
      "Scenario Name": "test scenario_1",
      "User": "PD00810869",
      "Scenario Id": "1",
      "Positions": [
        {
          "Deviations": [
            {
              "Expected value": "22.20000000",
              "Field Name": "C1",
              "Actual Value": "22.30000000"
            }
          ],
          "Page Name": "P1",
          "Session ID": "6e057dt99ae33t",
          "Tag Name": "HealthCheck"
        }
      ],
      "Screen Shots": [
        "E:\\gitClone\\demoBDDFramework\\screenShots\\07-Aug-2019__02_39_46PM\\2019_08_07T14_39_58_004443700.png",
        "E:\\gitClone\\demoBDDFramework\\screenShots\\07-Aug-2019__02_39_46PM\\2019_08_07T14_43_28_970857100.png",
        "E:\\gitClone\\demoBDDFramework\\screenShots\\07-Aug-2019__02_39_46PM\\2019_08_07T14_50_50_689343400.png"
      ],
      "ID": 1,
      "Date": "2022-07-14"
    }
  ]
}